lib.py
models.py
tmail_link_client-0.2.0.dist-info/METADATA
tmail_link_client-0.2.0.dist-info/WHEEL
tmail_link_client-0.2.0.dist-info/top_level.txt
tmail_link_client-0.2.0.dist-info/RECORD
