Metadata-Version: 2.4
Name: tmail-link-client
Version: 0.2.0
Summary: an python client of disposable temporary email provider https://tmail.link
Requires-Python: >=3.13
Requires-Dist: beautifulsoup4>=4.13.4
Requires-Dist: curl-cffi>=0.13.0
Requires-Dist: pydantic>=2.11.7
Requires-Dist: pydash>=8.0.5
